[
  {
    "FilerStateId": "1386932",
    "Tran_Amt1": 300.0,
    "Tran_Date": "2016-08-18",
    "Tran_NamF": "Ernesto Jose",
    "Tran_NamL": "Arevalo"
  },
  {
    "FilerStateId": "1386932",
    "Tran_Amt1": 100.0,
    "Tran_Date": "2016-09-16",
    "Tran_NamF": "Ernesto Jose",
    "Tran_NamL": "Arevalo"
  },
  {
    "FilerStateId": "1386932",
    "Tran_Amt1": 200.0,
    "Tran_Date": "2016-09-15",
    "Tran_NamF": "Moraa",
    "Tran_NamL": "Bey"
  },
  {
    "FilerStateId": "1386932",
    "Tran_Amt1": 700.0,
    "Tran_Date": "2016-09-13",
    "Tran_NamF": "Lewis",
    "Tran_NamL": "Bundy"
  },
  {
    "FilerStateId": "1386932",
    "Tran_Amt1": 100.0,
    "Tran_Date": "2016-09-16",
    "Tran_NamF": "Arnold",
    "Tran_NamL": "Chandler"
  },
  {
    "FilerStateId": "1386932",
    "Tran_Amt1": 700.0,
    "Tran_Date": "2016-08-21",
    "Tran_NamF": "Sharon",
    "Tran_NamL": "Cornu-Toney"
  },
  {
    "FilerStateId": "1386932",
    "Tran_Amt1": 200.0,
    "Tran_Date": "2016-09-15",
    "Tran_NamF": "Sandra",
    "Tran_NamL": "Davis"
  },
  {
    "FilerStateId": "1386932",
    "Tran_Amt1": 500.0,
    "Tran_Date": "2016-08-11",
    "Tran_NamF": "Sandra",
    "Tran_NamL": "Davis"
  },
  {
    "FilerStateId": "1386932",
    "Tran_Amt1": 250.0,
    "Tran_Date": "2016-09-15",
    "Tran_NamF": "Alexandra",
    "Tran_NamL": "Desautels"
  },
  {
    "FilerStateId": "1386932",
    "Tran_Amt1": 200.0,
    "Tran_Date": "2016-09-24",
    "Tran_NamF": "Kathryn Kelly",
    "Tran_NamL": "Epstein"
  },
  {
    "FilerStateId": "1386932",
    "Tran_Amt1": 100.0,
    "Tran_Date": "2016-09-16",
    "Tran_NamF": "Amy",
    "Tran_NamL": "Fitzgerald"
  },
  {
    "FilerStateId": "1386932",
    "Tran_Amt1": 100.0,
    "Tran_Date": "2016-09-16",
    "Tran_NamF": "Shawn",
    "Tran_NamL": "Ginwright"
  },
  {
    "FilerStateId": "1386932",
    "Tran_Amt1": 100.0,
    "Tran_Date": "2016-08-07",
    "Tran_NamF": "Deborah",
    "Tran_NamL": "Hailu"
  },
  {
    "FilerStateId": "1386932",
    "Tran_Amt1": 500.0,
    "Tran_Date": "2016-09-02",
    "Tran_NamF": "Gregory",
    "Tran_NamL": "Hodge"
  },
  {
    "FilerStateId": "1386932",
    "Tran_Amt1": 100.0,
    "Tran_Date": "2016-08-03",
    "Tran_NamF": "Carolyn",
    "Tran_NamL": "Holloway"
  },
  {
    "FilerStateId": "1386932",
    "Tran_Amt1": 150.0,
    "Tran_Date": "2016-08-18",
    "Tran_NamF": "Mtafiti",
    "Tran_NamL": "Imara"
  },
  {
    "FilerStateId": "1386932",
    "Tran_Amt1": 150.0,
    "Tran_Date": "2016-08-03",
    "Tran_NamF": "Nia M.",
    "Tran_NamL": "Imara"
  },
  {
    "FilerStateId": "1386932",
    "Tran_Amt1": 200.0,
    "Tran_Date": "2016-09-16",
    "Tran_NamF": "Kathryn",
    "Tran_NamL": "Kasch"
  },
  {
    "FilerStateId": "1386932",
    "Tran_Amt1": 200.0,
    "Tran_Date": "2016-09-15",
    "Tran_NamF": "Michael V.",
    "Tran_NamL": "Kaufman"
  },
  {
    "FilerStateId": "1386932",
    "Tran_Amt1": 200.0,
    "Tran_Date": "2016-09-08",
    "Tran_NamF": "Michael V.",
    "Tran_NamL": "Kaufman"
  },
  {
    "FilerStateId": "1386932",
    "Tran_Amt1": 300.0,
    "Tran_Date": "2016-08-01",
    "Tran_NamF": "Michael V.",
    "Tran_NamL": "Kaufman"
  },
  {
    "FilerStateId": "1386932",
    "Tran_Amt1": 100.0,
    "Tran_Date": "2016-08-18",
    "Tran_NamF": "Pierre M.",
    "Tran_NamL": "Labossiere"
  },
  {
    "FilerStateId": "1386932",
    "Tran_Amt1": 200.0,
    "Tran_Date": "2016-09-24",
    "Tran_NamF": null,
    "Tran_NamL": "League of Conservation Voters of the East Bay"
  },
  {
    "FilerStateId": "1386932",
    "Tran_Amt1": 150.0,
    "Tran_Date": "2016-09-08",
    "Tran_NamF": "Matthew",
    "Tran_NamL": "Leber"
  },
  {
    "FilerStateId": "1386932",
    "Tran_Amt1": 200.0,
    "Tran_Date": "2016-09-24",
    "Tran_NamF": "Anna",
    "Tran_NamL": "Lee"
  },
  {
    "FilerStateId": "1386932",
    "Tran_Amt1": 250.0,
    "Tran_Date": "2016-09-16",
    "Tran_NamF": "Luke",
    "Tran_NamL": "Newton"
  },
  {
    "FilerStateId": "1386932",
    "Tran_Amt1": 100.0,
    "Tran_Date": "2016-09-13",
    "Tran_NamF": "Edward",
    "Tran_NamL": "Page"
  },
  {
    "FilerStateId": "1386932",
    "Tran_Amt1": 150.0,
    "Tran_Date": "2016-08-04",
    "Tran_NamF": "Arnold",
    "Tran_NamL": "Perkins"
  },
  {
    "FilerStateId": "1386932",
    "Tran_Amt1": 250.0,
    "Tran_Date": "2016-09-16",
    "Tran_NamF": "Roberts",
    "Tran_NamL": "Phillips"
  },
  {
    "FilerStateId": "1386932",
    "Tran_Amt1": 100.0,
    "Tran_Date": "2016-09-16",
    "Tran_NamF": "Castle",
    "Tran_NamL": "Redmond"
  },
  {
    "FilerStateId": "1386932",
    "Tran_Amt1": 50.0,
    "Tran_Date": "2016-09-24",
    "Tran_NamF": "Sharon A.",
    "Tran_NamL": "Rice"
  },
  {
    "FilerStateId": "1386932",
    "Tran_Amt1": 100.0,
    "Tran_Date": "2016-08-02",
    "Tran_NamF": "Sharon A.",
    "Tran_NamL": "Rice"
  },
  {
    "FilerStateId": "1386932",
    "Tran_Amt1": 200.0,
    "Tran_Date": "2016-09-14",
    "Tran_NamF": "Walter",
    "Tran_NamL": "Riley"
  },
  {
    "FilerStateId": "1386932",
    "Tran_Amt1": 100.0,
    "Tran_Date": "2016-09-16",
    "Tran_NamF": "Linda",
    "Tran_NamL": "Roman"
  },
  {
    "FilerStateId": "1386932",
    "Tran_Amt1": 250.0,
    "Tran_Date": "2016-09-14",
    "Tran_NamF": "Susan",
    "Tran_NamL": "Schacher"
  },
  {
    "FilerStateId": "1386932",
    "Tran_Amt1": 100.0,
    "Tran_Date": "2016-09-24",
    "Tran_NamF": "Rasheed",
    "Tran_NamL": "Shabazz"
  },
  {
    "FilerStateId": "1386932",
    "Tran_Amt1": 500.0,
    "Tran_Date": "2016-09-13",
    "Tran_NamF": "Shiree",
    "Tran_NamL": "Teng"
  },
  {
    "FilerStateId": "1386932",
    "Tran_Amt1": 100.0,
    "Tran_Date": "2016-09-24",
    "Tran_NamF": "Sacy",
    "Tran_NamL": "Thompson"
  },
  {
    "FilerStateId": "1386932",
    "Tran_Amt1": 1500.0,
    "Tran_Date": "2016-09-16",
    "Tran_NamF": null,
    "Tran_NamL": "Transport Oakland"
  },
  {
    "FilerStateId": "1386932",
    "Tran_Amt1": 400.0,
    "Tran_Date": "2016-09-16",
    "Tran_NamF": "Sandra",
    "Tran_NamL": "Witt"
  },
  {
    "FilerStateId": "1386932",
    "Tran_Amt1": 200.0,
    "Tran_Date": "2016-09-15",
    "Tran_NamF": "Daniel",
    "Tran_NamL": "Zingale"
  }
]
